README.rst
setup.py
efb_qq_plugin_iot/ChatMgr.py
efb_qq_plugin_iot/CustomTypes.py
efb_qq_plugin_iot/IOTBot.py
efb_qq_plugin_iot/IOTConfig.py
efb_qq_plugin_iot/IOTFactory.py
efb_qq_plugin_iot/IOTMsgProcessor.py
efb_qq_plugin_iot/MsgDecorator.py
efb_qq_plugin_iot/Utils.py
efb_qq_plugin_iot/__init__.py
efb_qq_plugin_iot/__version__.py
efb_qq_plugin_iot.egg-info/PKG-INFO
efb_qq_plugin_iot.egg-info/SOURCES.txt
efb_qq_plugin_iot.egg-info/dependency_links.txt
efb_qq_plugin_iot.egg-info/entry_points.txt
efb_qq_plugin_iot.egg-info/requires.txt
efb_qq_plugin_iot.egg-info/top_level.txt
lib/silkv3/src/Decoder.c
lib/silkv3/src/SKP_Silk_A2NLSF.c
lib/silkv3/src/SKP_Silk_CNG.c
lib/silkv3/src/SKP_Silk_HP_variable_cutoff_FIX.c
lib/silkv3/src/SKP_Silk_LBRR_reset.c
lib/silkv3/src/SKP_Silk_LPC_inv_pred_gain.c
lib/silkv3/src/SKP_Silk_LPC_synthesis_filter.c
lib/silkv3/src/SKP_Silk_LPC_synthesis_order16.c
lib/silkv3/src/SKP_Silk_LP_variable_cutoff.c
lib/silkv3/src/SKP_Silk_LSF_cos_table.c
lib/silkv3/src/SKP_Silk_LTP_analysis_filter_FIX.c
lib/silkv3/src/SKP_Silk_LTP_scale_ctrl_FIX.c
lib/silkv3/src/SKP_Silk_MA.c
lib/silkv3/src/SKP_Silk_NLSF2A.c
lib/silkv3/src/SKP_Silk_NLSF2A_stable.c
lib/silkv3/src/SKP_Silk_NLSF_MSVQ_decode.c
lib/silkv3/src/SKP_Silk_NLSF_MSVQ_encode_FIX.c
lib/silkv3/src/SKP_Silk_NLSF_VQ_rate_distortion_FIX.c
lib/silkv3/src/SKP_Silk_NLSF_VQ_sum_error_FIX.c
lib/silkv3/src/SKP_Silk_NLSF_VQ_weights_laroia.c
lib/silkv3/src/SKP_Silk_NLSF_stabilize.c
lib/silkv3/src/SKP_Silk_NSQ.c
lib/silkv3/src/SKP_Silk_NSQ_del_dec.c
lib/silkv3/src/SKP_Silk_PLC.c
lib/silkv3/src/SKP_Silk_VAD.c
lib/silkv3/src/SKP_Silk_VQ_nearest_neighbor_FIX.c
lib/silkv3/src/SKP_Silk_ana_filt_bank_1.c
lib/silkv3/src/SKP_Silk_apply_sine_window.c
lib/silkv3/src/SKP_Silk_array_maxabs.c
lib/silkv3/src/SKP_Silk_autocorr.c
lib/silkv3/src/SKP_Silk_biquad.c
lib/silkv3/src/SKP_Silk_biquad_alt.c
lib/silkv3/src/SKP_Silk_burg_modified.c
lib/silkv3/src/SKP_Silk_bwexpander.c
lib/silkv3/src/SKP_Silk_bwexpander_32.c
lib/silkv3/src/SKP_Silk_code_signs.c
lib/silkv3/src/SKP_Silk_control_audio_bandwidth.c
lib/silkv3/src/SKP_Silk_control_codec_FIX.c
lib/silkv3/src/SKP_Silk_corrMatrix_FIX.c
lib/silkv3/src/SKP_Silk_create_init_destroy.c
lib/silkv3/src/SKP_Silk_dec_API.c
